logio/__init__.py
logio/cli.py
logio/logfilter.py
logio/login.py
logio/logout.py
logio/logparser.py
logio/rules.py
logio/tests/__init__.py
logio/tests/test_logparse.py
logio-0.1.21.dist-info/licenses/LICENSE
logio-0.1.21.dist-info/METADATA
logio-0.1.21.dist-info/WHEEL
logio-0.1.21.dist-info/entry_points.txt
logio-0.1.21.dist-info/top_level.txt
logio-0.1.21.dist-info/RECORD
