Metadata-Version: 2.4
Name: logio
Version: 0.1.21
Summary: Parse log file as input and export the data to database as output.
Author: rRR0VrFP
Maintainer: rRR0VrFP
License: MIT
Keywords: logio
Classifier: Development Status :: 5 - Production/Stable
Classifier: Intended Audience :: Developers
Classifier: Topic :: Software Development :: Libraries :: Python Modules
Classifier: License :: OSI Approved :: MIT License
Classifier: Programming Language :: Python :: 3
Classifier: Programming Language :: Python :: 3 :: Only
License-File: LICENSE
Requires-Dist: click
Requires-Dist: pyyaml
Requires-Dist: tail
Requires-Dist: fastutils
Requires-Dist: sympy
Dynamic: author
Dynamic: classifier
Dynamic: description
Dynamic: description-content-type
Dynamic: keywords
Dynamic: license
Dynamic: license-file
Dynamic: maintainer
Dynamic: requires-dist
Dynamic: summary
